{
  "trainingPhrases": [ {
    "parts": [ {
      "text": "con chi ho il piacere di parlare"
    } ],
    "repeatCount": 1,
    "languageCode": "it"
  }, {
    "parts": [ {
      "text": "posso sapere il tuo nome"
    } ],
    "repeatCount": 1,
    "languageCode": "it"
  }, {
    "parts": [ {
      "text": "quanti ani gheto nome",
      "auto": true
    } ],
    "repeatCount": 1,
    "languageCode": "it"
  }, {
    "parts": [ {
      "text": "con chi sto parlando"
    } ],
    "repeatCount": 1,
    "languageCode": "it"
  }, {
    "parts": [ {
      "text": "sei un chatbot"
    } ],
    "repeatCount": 1,
    "languageCode": "it"
  }, {
    "parts": [ {
      "text": "sei un bot"
    } ],
    "repeatCount": 1,
    "languageCode": "it"
  }, {
    "parts": [ {
      "text": "sei un robot"
    } ],
    "repeatCount": 1,
    "languageCode": "it"
  }, {
    "parts": [ {
      "text": "sei un replicante"
    } ],
    "repeatCount": 1,
    "languageCode": "it"
  }, {
    "parts": [ {
      "text": "chi sono i tuoi creatori"
    } ],
    "repeatCount": 1,
    "languageCode": "it"
  }, {
    "parts": [ {
      "text": "chi sei"
    } ],
    "repeatCount": 1,
    "languageCode": "it"
  } ]
}
