{
  "excludedPhrases": [ {
    "value": "sbloccare una mia",
    "languageCode": "it"
  }, {
    "value": "sbloccare la mia",
    "languageCode": "it"
  }, {
    "value": "sblocco di una mia",
    "languageCode": "it"
  }, {
    "value": "sblocco della mia",
    "languageCode": "it"
  }, {
    "value": "sbloccare mia",
    "languageCode": "it"
  }, {
    "value": "sblocco mia",
    "languageCode": "it"
  }, {
    "value": "no la voglio sbloccare",
    "languageCode": "it"
  }, {
    "value": "vorrei sbloccarla",
    "languageCode": "it"
  }, {
    "value": "voglio sbloccare",
    "languageCode": "it"
  } ]
}
