{
  "trainingPhrases": [ {
    "parts": [ {
      "text": "vorrei conferma degli ineseguiti",
      "auto": true
    } ],
    "repeatCount": 1,
    "languageCode": "it"
  }, {
    "parts": [ {
      "text": "mi dai ",
      "auto": true
    }, {
      "text": "l'",
      "auto": true
    }, {
      "text": "elenco degli ineseguiti?",
      "auto": true
    } ],
    "repeatCount": 1,
    "languageCode": "it"
  }, {
    "parts": [ {
      "text": "mi serve ",
      "auto": true
    }, {
      "text": "l'",
      "auto": true
    }, {
      "text": "elenco degli ineseguiti?",
      "auto": true
    } ],
    "repeatCount": 1,
    "languageCode": "it"
  }, {
    "parts": [ {
      "text": "posso verificare ",
      "auto": true
    }, {
      "text": "se",
      "auto": true
    }, {
      "text": " ho degli ineseguiti in ",
      "auto": true
    }, {
      "text": "titoli",
      "auto": true
    }, {
      "text": "?",
      "auto": true
    } ],
    "repeatCount": 1,
    "languageCode": "it"
  }, {
    "parts": [ {
      "text": "cerco gli ineseguiti in titoli",
      "auto": true
    } ],
    "repeatCount": 1,
    "languageCode": "it"
  }, {
    "parts": [ {
      "text": "posso vedere gli ineseguiti",
      "auto": true
    } ],
    "repeatCount": 1,
    "languageCode": "it"
  } ]
}
